setup.cfg
setup.py
tgrum.py
TgRum.egg-info/PKG-INFO
TgRum.egg-info/SOURCES.txt
TgRum.egg-info/dependency_links.txt
TgRum.egg-info/requires.txt
TgRum.egg-info/top_level.txt
TgRum.egg-info/zip-safe