Metadata-Version: 1.0
Name: TgRum
Version: 0.3.2dev-20100628
Summary: Some helpers to integrate Rum nicely into TurboGears
Home-page: http://python-rum.org/
Author: Alberto Valverde Gonzalez, Michael Brickenstein
Author-email: info@python-rum.org
License: MIT
Keywords: Turbogears Rum wsgi
Platform: UNKNOWN
